pythia8mc.cpython-312-darwin.so
pythia8mc-8.317.0.data/data/share/Pythia8/htmldoc/AdvancedUsage.html
pythia8mc-8.317.0.data/data/share/Pythia8/htmldoc/AlpgenEventInterface.html
pythia8mc-8.317.0.data/data/share/Pythia8/htmldoc/BeamParameters.html
pythia8mc-8.317.0.data/data/share/Pythia8/htmldoc/BeamRemnants.html
pythia8mc-8.317.0.data/data/share/Pythia8/htmldoc/BeamShape.html
pythia8mc-8.317.0.data/data/share/Pythia8/htmldoc/Bibliography.html
pythia8mc-8.317.0.data/data/share/Pythia8/htmldoc/BoseEinsteinEffects.html
pythia8mc-8.317.0.data/data/share/Pythia8/htmldoc/CKKWLMerging.html
pythia8mc-8.317.0.data/data/share/Pythia8/htmldoc/COPYING
pythia8mc-8.317.0.data/data/share/Pythia8/htmldoc/ClosePacking.html
pythia8mc-8.317.0.data/data/share/Pythia8/htmldoc/ColourReconnection.html
pythia8mc-8.317.0.data/data/share/Pythia8/htmldoc/CompositenessProcesses.html
pythia8mc-8.317.0.data/data/share/Pythia8/htmldoc/CouplingsAndScales.html
pythia8mc-8.317.0.data/data/share/Pythia8/htmldoc/CrossSectionsAndWeights.html
pythia8mc-8.317.0.data/data/share/Pythia8/htmldoc/DarkMatterProcesses.html
pythia8mc-8.317.0.data/data/share/Pythia8/htmldoc/DeuteronProduction.html
pythia8mc-8.317.0.data/data/share/Pythia8/htmldoc/Diffraction.html
pythia8mc-8.317.0.data/data/share/Pythia8/htmldoc/ElectroweakProcesses.html
pythia8mc-8.317.0.data/data/share/Pythia8/htmldoc/ErrorChecks.html
pythia8mc-8.317.0.data/data/share/Pythia8/htmldoc/EventAnalysis.html
pythia8mc-8.317.0.data/data/share/Pythia8/htmldoc/EventInformation.html
pythia8mc-8.317.0.data/data/share/Pythia8/htmldoc/EventRecord.html
pythia8mc-8.317.0.data/data/share/Pythia8/htmldoc/EventStatistics.html
pythia8mc-8.317.0.data/data/share/Pythia8/htmldoc/ExampleKeywords.html
pythia8mc-8.317.0.data/data/share/Pythia8/htmldoc/Examples.js
pythia8mc-8.317.0.data/data/share/Pythia8/htmldoc/Expand.js
pythia8mc-8.317.0.data/data/share/Pythia8/htmldoc/ExternalDecays.html
pythia8mc-8.317.0.dist-info/METADATA
pythia8mc-8.317.0.dist-info/WHEEL
pythia8mc-8.317.0.dist-info/top_level.txt
pythia8mc-8.317.0.dist-info/RECORD
