Metadata-Version: 2.2
Name: pythia8mc
Version: 8.317.0
Summary: General purpose particle physics Monte Carlo generator.
Home-page: https://pythia.org
Download-URL: https://pythia.org/download/pythia83/pythia8317.tgz
Author: Pythia 8 Team
Author-email: authors@pythia.org
License: GNU GPL v2 or later
Project-URL: Documentation, https://pythia.org/manuals/pythia8317/Welcome.html
Project-URL: Physics Manual, https://pythia.org/pdfdoc/pythia8300.pdf
Project-URL: Doxygen, https://pythia.org/doxygen/pythia8317/
Project-URL: Issue Desk, https://gitlab.com/Pythia8/releases/-/issues
Project-URL: Source Repository, https://gitlab.com/Pythia8/releases
Platform: Linux
Platform: MacOS
Dynamic: author
Dynamic: author-email
Dynamic: description
Dynamic: description-content-type
Dynamic: download-url
Dynamic: home-page
Dynamic: license
Dynamic: platform
Dynamic: project-url
Dynamic: summary
